{
    "averageScore": {
        "1 Adet Golden But": 4,
        "1 Parça Acılı Kanat (Wings)": 4,
        "1 Parça But": 3,
        "1 Parça Kaburga": 4,
        "1 Parça Kalça": 4,
        "1 Parça Tavuk Göğüs": 3,
        "1 Parça Tender (Kemiksiz)": 4,
        "10'lu Dip’n Chicken": 0,
        "10'lu Dip’n Chicken Menü": 5,
        "10'lu Nuggets": 1,
        "10'lu Nuggets Menü": 4,
        "10'lu Wicked Chicken": 0,
        "10'lu Wicked Chicken Menü": 5,
        "15'li Dip’n Chicken": 0,
        "15'li Dip’n Chicken Menü": 5,
        "15'li Nuggets": 1,
        "15'li Nuggets Menü": 4,
        "15'li Wicked Chicken": 0,
        "15'li Wicked Chicken Menü": 5,
        "2 Adet Golden But": 4,
        "2 Kişilik Ekonomik Menü": 4,
        "2 Kişilik Kanat Maxi Kova Menü": 4,
        "2 Kişilik Karışık Maxi Kova Menü": 4,
        "2 Kişilik Kemiksiz Maxi Kova Menü": 4,
        "2 Kişilik Parça Tavuk Maxi Kova Menü": 3,
        "2 Parça Golden But Menü": 4,
        "2 Parça Tavuk Menü": 3,
        "2'li Maxi Menü": 5,
        "20'li Dip’n Chicken": 0,
        "20'li Dip’n Chicken Menü": 5,
        "20'li Nuggets": 1,
        "20'li Nuggets Menü": 4,
        "20'li Wicked Chicken": 0,
        "20'li Wicked Chicken Menü": 5,
        "3 'lü Tenders Menü (Kemiksiz)": 6,
        "3 Parça Acılı Kanat": 4,
        "3 Parça Tavuk Menü": 5,
        "4 Kişilik Kanat Maxi Kova": 5,
        "4 Kişilik Kanat Maxi Kova Menü": 5,
        "4 Kişilik Parça Tavuk Maxi Kova": 3,
        "4 Kişilik Parça Tavuk Maxi Kova Menü": 4,
        "4 Parça Tavuk Menü": 4,
        "5 Parça Acılı Kanat": 5,
        "5 Parça Acılı Kanat Menü": 5,
        "8 Parça Acılı Kanat": 4,
        "8 Parça Acılı Kanat Menü": 5,
        "Acı Sos": 7,
        "Acılı Barbekü Sos": 7,
        "Aile Kovası-Nuggets Menü": 4,
        "Aile Kovası-Çocuk Tavukburger® Menü": 4,
        "Baharatlı Tavuk Pilav": 4,
        "Biscuit": 0,
        "Blackened Ranch Sos": 7,
        "Buffalo Sos": 7,
        "Büyük Ayran (300 ml.)": 5,
        "Cage Fries (Patates Kızartması)": 4,
        "Chicken Deluxe Sandviç": 0,
        "Chicken Deluxe Sandwich Menü": 5,
        "Chipotle Sos": 7,
        "Coleslaw": 4,
        "Creole": 0,
        "Double Popchicken": 0,
        "Double Popchicken Menü": 5,
        "Elmalı Soda": 0,
        "Exotic Portakal Suyu (330 ml.)": 6,
        "Fruko (1,5 L.)": 0,
        "Fruko (33 cl.)": 0,
        "Futbol Kovası": 1,
        "Gravy Soslu Patates Püresi": 7,
        "Kazandıran Kova": 1,
        "Kazandıran Kova 2": 5,
        "Ketçap": 6,
        "Kova Boy Cage Fries (Patates Kızartması)": 5,
        "Kova Boy Normal Dilim (Patates Kızartması)": 4,
        "Küçük Ayran (200 ml.)": 0,
        "Limonata": 0,
        "Limonlu Soda": 0,
        "Lipton Ice Tea Limon (33 cl.)": 6,
        "Lipton Ice Tea Şeftali (33 cl.)": 6,
        "Maxi Avantaj Menü": 5,
        "Maxi Dip Menü": 5,
        "Maxi Menü": 5,
        "Maxi Menü (Nuggets'lı)": 5,
        "Maxi XL Menü": 5,
        "Maximum Menü (Chicken Deluxe Sandviç)": 5,
        "Mayonez": 6,
        "Mısır": 4,
        "Normal Dilim Patates Kızartması": 8,
        "Nuggets Salata": 1,
        "Nuggets Salata Menü": 4,
        "Panini Gusto Menü": 5,
        "Panini Gusto Sandviç": 0,
        "Pepsi (1 L.)": 0,
        "Pepsi (33 cl.)": 0,
        "Pepsi Light (1 L.)": 0,
        "Pepsi Light (33 cl.)": 0,
        "Pepsi Max (1 L.)": 0,
        "Pepsi Max (33 cl.)": 0,
        "Popchicken": 0,
        "Popchicken Menü": 5,
        "Poproll": 0,
        "Poproll Menü": 5,
        "Pro Gamer Menü": 5,
        "Pro Gamer Menü 2": 5,
        "Profiterol": 0,
        "Sade Soda": 8,
        "Salata Sosu": 7,
        "Sarımsaklı Parmesanlı Mayonez": 6,
        "Susamlı Soğan Halkası": 7,
        "Tavukburger®": 0,
        "Tavukburger® Menü": 5,
        "Trend Menü": 5,
        "Vodafone Menüsü 1": 4,
        "Vodafone Menüsü 2": 5,
        "Yedigün (1 L.)": 0,
        "Yedigün (33 cl.)": 0,
        "Çocuk Menüsü": 1,
        "Çocuk Tavukburger®": 0
    },
    "commentCount": {
        "1 Adet Golden But": 26,
        "1 Parça Acılı Kanat (Wings)": 26,
        "1 Parça But": 25,
        "1 Parça Kaburga": 23,
        "1 Parça Kalça": 23,
        "1 Parça Tavuk Göğüs": 32,
        "1 Parça Tender (Kemiksiz)": 23,
        "10'lu Dip’n Chicken": 0,
        "10'lu Dip’n Chicken Menü": 7,
        "10'lu Nuggets": 1,
        "10'lu Nuggets Menü": 8,
        "10'lu Wicked Chicken": 0,
        "10'lu Wicked Chicken Menü": 7,
        "15'li Dip’n Chicken": 0,
        "15'li Dip’n Chicken Menü": 7,
        "15'li Nuggets": 1,
        "15'li Nuggets Menü": 8,
        "15'li Wicked Chicken": 0,
        "15'li Wicked Chicken Menü": 7,
        "2 Adet Golden But": 16,
        "2 Kişilik Ekonomik Menü": 23,
        "2 Kişilik Kanat Maxi Kova Menü": 26,
        "2 Kişilik Karışık Maxi Kova Menü": 24,
        "2 Kişilik Kemiksiz Maxi Kova Menü": 24,
        "2 Kişilik Parça Tavuk Maxi Kova Menü": 33,
        "2 Parça Golden But Menü": 22,
        "2 Parça Tavuk Menü": 29,
        "2'li Maxi Menü": 7,
        "20'li Dip’n Chicken": 0,
        "20'li Dip’n Chicken Menü": 7,
        "20'li Nuggets": 1,
        "20'li Nuggets Menü": 8,
        "20'li Wicked Chicken": 0,
        "20'li Wicked Chicken Menü": 7,
        "3 'lü Tenders Menü (Kemiksiz)": 10,
        "3 Parça Acılı Kanat": 6,
        "3 Parça Tavuk Menü": 19,
        "4 Kişilik Kanat Maxi Kova": 11,
        "4 Kişilik Kanat Maxi Kova Menü": 18,
        "4 Kişilik Parça Tavuk Maxi Kova": 18,
        "4 Kişilik Parça Tavuk Maxi Kova Menü": 25,
        "4 Parça Tavuk Menü": 21,
        "5 Parça Acılı Kanat": 13,
        "5 Parça Acılı Kanat Menü": 20,
        "8 Parça Acılı Kanat": 5,
        "8 Parça Acılı Kanat Menü": 12,
        "Acı Sos": 21,
        "Acılı Barbekü Sos": 20,
        "Aile Kovası-Nuggets Menü": 8,
        "Aile Kovası-Çocuk Tavukburger® Menü": 8,
        "Baharatlı Tavuk Pilav": 12,
        "Biscuit": 0,
        "Blackened Ranch Sos": 18,
        "Buffalo Sos": 19,
        "Büyük Ayran (300 ml.)": 5,
        "Cage Fries (Patates Kızartması)": 8,
        "Chicken Deluxe Sandviç": 0,
        "Chicken Deluxe Sandwich Menü": 7,
        "Chipotle Sos": 18,
        "Coleslaw": 1,
        "Creole": 0,
        "Double Popchicken": 0,
        "Double Popchicken Menü": 7,
        "Elmalı Soda": 0,
        "Exotic Portakal Suyu (330 ml.)": 1,
        "Fruko (1,5 L.)": 0,
        "Fruko (33 cl.)": 0,
        "Futbol Kovası": 1,
        "Gravy Soslu Patates Püresi": 37,
        "Kazandıran Kova": 1,
        "Kazandıran Kova 2": 14,
        "Ketçap": 2,
        "Kova Boy Cage Fries (Patates Kızartması)": 12,
        "Kova Boy Normal Dilim (Patates Kızartması)": 23,
        "Küçük Ayran (200 ml.)": 0,
        "Limonata": 0,
        "Limonlu Soda": 0,
        "Lipton Ice Tea Limon (33 cl.)": 1,
        "Lipton Ice Tea Şeftali (33 cl.)": 1,
        "Maxi Avantaj Menü": 7,
        "Maxi Dip Menü": 7,
        "Maxi Menü": 7,
        "Maxi Menü (Nuggets'lı)": 7,
        "Maxi XL Menü": 7,
        "Maximum Menü (Chicken Deluxe Sandviç)": 7,
        "Mayonez": 2,
        "Mısır": 2,
        "Normal Dilim Patates Kızartması": 58,
        "Nuggets Salata": 1,
        "Nuggets Salata Menü": 8,
        "Panini Gusto Menü": 7,
        "Panini Gusto Sandviç": 0,
        "Pepsi (1 L.)": 0,
        "Pepsi (33 cl.)": 0,
        "Pepsi Light (1 L.)": 0,
        "Pepsi Light (33 cl.)": 0,
        "Pepsi Max (1 L.)": 0,
        "Pepsi Max (33 cl.)": 0,
        "Popchicken": 0,
        "Popchicken Menü": 7,
        "Poproll": 0,
        "Poproll Menü": 7,
        "Pro Gamer Menü": 7,
        "Pro Gamer Menü 2": 20,
        "Profiterol": 0,
        "Sade Soda": 5,
        "Salata Sosu": 1,
        "Sarımsaklı Parmesanlı Mayonez": 2,
        "Susamlı Soğan Halkası": 2,
        "Tavukburger®": 0,
        "Tavukburger® Menü": 7,
        "Trend Menü": 7,
        "Vodafone Menüsü 1": 24,
        "Vodafone Menüsü 2": 14,
        "Yedigün (1 L.)": 0,
        "Yedigün (33 cl.)": 0,
        "Çocuk Menüsü": 1,
        "Çocuk Tavukburger®": 0
    }
}